setup.cfg
setup.py
testbywyf/__init__.py
testbywyf/test.py
testbywyf/wyfFuncs.py
testbywyf.egg-info/PKG-INFO
testbywyf.egg-info/SOURCES.txt
testbywyf.egg-info/dependency_links.txt
testbywyf.egg-info/not-zip-safe
testbywyf.egg-info/top_level.txt