Metadata-Version: 1.1
Name: testbywyf
Version: 0.1.0
Summary: this is a test package for packing python liberaries tutorial.
Home-page: https://github.com/Weber-JC/testbywyf
Author: Weber Juche
Author-email: weber.juche@gmail.com
License: MIT
Keywords: test python package
Platform: UNKNOWN
Classifier: License :: OSI Approved :: MIT License
Classifier: Programming Language :: Python
Classifier: Intended Audience :: Developers
Classifier: Operating System :: OS Independent
